chino/__init__.py
chino/api.py
chino/exceptions.py
chino/objects.py
chino-2.14.0.dist-info/AUTHORS.md
chino-2.14.0.dist-info/METADATA
chino-2.14.0.dist-info/WHEEL
chino-2.14.0.dist-info/pbr.json
chino-2.14.0.dist-info/top_level.txt
chino-2.14.0.dist-info/RECORD
