Metadata-Version: 2.1
Name: chino
Version: 2.14.0
Summary: Wrapper for Chino.io API
Home-page: https://www.chino.io
Author: Chino.io
Author-email: dev@chino.io
License: MIT
Project-URL: Source Code, https://gitlab.com/chinoio-public/chino-python
Platform: UNKNOWN
Classifier: Topic :: Software Development
Classifier: Development Status :: 5 - Production/Stable
Classifier: Programming Language :: Python :: 2
Classifier: Programming Language :: Python :: 3
License-File: AUTHORS.md
Requires-Dist: requests (<=3,>=2.9.1)
Requires-Dist: deprecation
Requires-Dist: nose
Requires-Dist: coverage
Requires-Dist: pytz
